etptool/__init__.py
etptool/__main__.py
etptool/version.py
etptool/_helper/cli.py
etptool/adc/__init__.py
etptool/adc/__main__.py
etptool/cfg/__init__.py
etptool/cfg/__main__.py
etptool/fw/__init__.py
etptool/fw/__main__.py
etptool/gpio/__init__.py
etptool/gpio/__main__.py
etptool/i2c/__init__.py
etptool/i2c/__main__.py
etptool/pwm/__init__.py
etptool/pwm/__main__.py
etptool/spi/__init__.py
etptool/spi/__main__.py
etptool/webui/__init__.py
etptool/webui/__main__.py
etptool/webui/index.html
etptool/webui/css/style.css
etptool-0.0.1.data/data/share/bash-completion/completions/etptool
etptool-0.0.1.dist-info/LICENSE
etptool-0.0.1.dist-info/METADATA
etptool-0.0.1.dist-info/WHEEL
etptool-0.0.1.dist-info/entry_points.txt
etptool-0.0.1.dist-info/top_level.txt
etptool-0.0.1.dist-info/RECORD
