Metadata-Version: 2.1
Name: etptool
Version: 0.0.1
Summary: Embedded Tester Protocol (ETP) Tool
Author-email: Jabez Winston <jabezwinston@gmail.com>, Stephen Kingston <stephen.psk@gmail.com>
License: MIT
Project-URL: Homepage, https://www.embeddedtester.com/
Project-URL: Source code, https://github.com/jabezwinston/etptool
Keywords: embedded,firmware,test,protocol,gpio,i2c,adc,pwm
Classifier: Programming Language :: Python :: 3
Classifier: License :: OSI Approved :: MIT License
Classifier: Operating System :: Microsoft :: Windows
Classifier: Operating System :: POSIX :: Linux
Classifier: Operating System :: MacOS :: MacOS X
Requires-Python: >=3.6
License-File: LICENSE
Requires-Dist: pyserial
Requires-Dist: etplib==0.2.1
